altf1be_sca_tork_easycube_api/__init__.py
altf1be_sca_tork_easycube_api/dispensers.py
altf1be_sca_tork_easycube_api/dispensers_model.py
altf1be_sca_tork_easycube_api/sca_tork_easycube_api.py
altf1be_sca_tork_easycube_api/sca_tork_easycube_api_authentication.py
altf1be_sca_tork_easycube_api/sca_tork_easycube_api_helpers.py
altf1be_sca_tork_easycube_api-1.1.0.dist-info/LICENSE
altf1be_sca_tork_easycube_api-1.1.0.dist-info/METADATA
altf1be_sca_tork_easycube_api-1.1.0.dist-info/WHEEL
altf1be_sca_tork_easycube_api-1.1.0.dist-info/top_level.txt
altf1be_sca_tork_easycube_api-1.1.0.dist-info/RECORD
