Metadata-Version: 2.1
Name: altf1be-sca-tork-easycube-api
Version: 1.1.0
Summary: Wrapper for python developers to connect to SCA Tork EasyCube API built by www.alt-f1.be
Home-page: https://abdelkrim@bitbucket.org/altf1be/com_torkglobal_easycube_fm
Author: Abdelkrim Boujraf
Author-email: abo+altf1be_sca_tork_easycube_api_pkg@alt-f1.be
License: UNLICENSED
Project-URL: Bug Reports, https://abdelkrim@bitbucket.org/altf1be/com_torkglobal_easycube_fm/admin/issues
Project-URL: Company behind the library, http://www.alt-f1.be
Project-URL: Source, https://abdelkrim@bitbucket.org/altf1be/com_torkglobal_easycube_fm
Keywords: library,altf1be_sca_tork_easycube_api,alt-f1.be,helpers-library,python3,pypi-package
Platform: UNKNOWN
Classifier: Development Status :: 5 - Production/Stable
Classifier: Intended Audience :: Developers
Classifier: License :: OSI Approved :: European Union Public Licence 1.2 (EUPL 1.2)
Classifier: Operating System :: OS Independent
Classifier: Programming Language :: Python :: 3.8
Classifier: Topic :: Software Development :: Libraries :: Python Modules
Requires-Python: >=3.8
Requires-Dist: altf1be-google-analytics-helpers (==1.0.0)
Requires-Dist: altf1be-helpers (==2.2.1)
Requires-Dist: auth (==0.5.3)
Requires-Dist: extensions (==0.4)
Requires-Dist: flask-babel (==2.0.0)
Requires-Dist: flask-login (==0.5.0)
Requires-Dist: flask-migrate (==2.5.3)
Requires-Dist: flask-sqlalchemy (==2.4.4)
Requires-Dist: Flask (==1.1.2)
Requires-Dist: gevent (==20.9.0)
Requires-Dist: gunicorn (==20.0.4)
Requires-Dist: numpy (==1.19.4)
Requires-Dist: pandas (==1.1.5)
Requires-Dist: python-dateutil (==2.8.1)
Requires-Dist: python-dotenv (==0.15.0)
Requires-Dist: pytz (==2020.4)
Requires-Dist: requests (==2.25.0)
